resources/__init__.py
resources/api.py
resources/client.py
resources/exceptions.py
resources/live_streams.py
resources/media.py
resources/playback_ids.py
resources/signing_keys.py
python_test_sdk-0.1.0.dist-info/METADATA
python_test_sdk-0.1.0.dist-info/WHEEL
python_test_sdk-0.1.0.dist-info/top_level.txt
python_test_sdk-0.1.0.dist-info/RECORD
